<VideoStream timebaseNumerator="1" timebaseDenomenator="1000">
<Group pts="0" duration="9840" size="771724" />
<Group pts="10010" duration="9799" size="437912" />
<Group pts="19978" duration="9840" size="2414144" />
<Group pts="29988" duration="9840" size="1626966" />
<Group pts="39998" duration="6314" size="1318232" />
<Group pts="46421" duration="1025" size="26537" />
<Group pts="47464" duration="7462" size="2517180" />
<Group pts="55055" duration="4920" size="1787528" />
<Group pts="60060" duration="9840" size="6297732" />
<Group pts="70070" duration="9061" size="4980570" />
<Group pts="79288" duration="9840" size="5257733" />
<Group pts="89298" duration="9512" size="4309851" />
<Group pts="98974" duration="9840" size="4128876" />
<Group pts="108984" duration="9799" size="3831352" />
<Group pts="118952" duration="9840" size="2522860" />
<Group pts="128962" duration="9840" size="3010217" />
<Group pts="138972" duration="9840" size="3106060" />
<Group pts="148982" duration="9840" size="3037755" />
<Group pts="158992" duration="9840" size="3026384" />
<Group pts="169002" duration="4879" size="1246736" />
<Group pts="173965" duration="9840" size="2390276" />
<Group pts="183975" duration="8159" size="1856159" />
<Group pts="192275" duration="9840" size="3076331" />
<Group pts="202285" duration="3772" size="1226969" />
<Group pts="206123" duration="9840" size="3116097" />
<Group pts="216133" duration="3116" size="806791" />
<Group pts="219302" duration="3157" size="989219" />
<Group pts="222514" duration="9840" size="2060209" />
<Group pts="232524" duration="5822" size="1176113" />
<Group pts="238447" duration="6765" size="1438867" />
<Group pts="245328" duration="9840" size="2394411" />
<Group pts="255338" duration="9840" size="3929885" />
<Group pts="265348" duration="4961" size="2205958" />
<Group pts="270395" duration="9840" size="3515476" />
<Group pts="280405" duration="2747" size="934739" />
<Group pts="283200" duration="5945" size="2615379" />
<Group pts="289247" duration="9840" size="3920889" />
<Group pts="299257" duration="2173" size="580994" />
<Group pts="301468" duration="6601" size="1299286" />
<Group pts="308183" duration="3485" size="873157" />
<Group pts="311728" duration="2009" size="600624" />
<Group pts="313772" duration="2091" size="629532" />
<Group pts="315899" duration="5453" size="1192250" />
<Group pts="321446" duration="9840" size="2405798" />
<Group pts="331456" duration="3444" size="1132936" />
<Group pts="334960" duration="3485" size="905968" />
<Group pts="338505" duration="9840" size="2867011" />
<Group pts="348515" duration="6642" size="1706728" />
<Group pts="355272" duration="9840" size="2472725" />
<Group pts="365282" duration="9840" size="2774416" />
<Group pts="375292" duration="4838" size="1363400" />
<Group pts="380213" duration="2788" size="631661" />
<Group pts="383049" duration="3731" size="953626" />
<Group pts="386845" duration="5412" size="1313393" />
<Group pts="392350" duration="9840" size="2579847" />
<Group pts="402360" duration="6642" size="1749622" />
<Group pts="409117" duration="7134" size="1740696" />
<Group pts="416374" duration="6929" size="1907055" />
<Group pts="423423" duration="4428" size="1240875" />
<Group pts="427928" duration="9799" size="2581735" />
<Group pts="437896" duration="9840" size="3723844" />
<Group pts="447906" duration="9799" size="3666813" />
<Group pts="457874" duration="9799" size="4056709" />
<Group pts="467842" duration="6232" size="2976517" />
<Group pts="474182" duration="4428" size="1435955" />
<Group pts="478687" duration="2460" size="800857" />
<Group pts="481189" duration="3157" size="1183041" />
<Group pts="484401" duration="5904" size="1736067" />
<Group pts="490407" duration="1517" size="539069" />
<Group pts="491950" duration="4879" size="1514144" />
<Group pts="496913" duration="2993" size="1541573" />
<Group pts="499958" duration="4551" size="1599298" />
<Group pts="504587" duration="4838" size="2314895" />
<Group pts="509509" duration="3731" size="1316032" />
<Group pts="513304" duration="1886" size="525780" />
<Group pts="515223" duration="2993" size="1366316" />
<Group pts="518268" duration="4551" size="1011612" />
<Group pts="522897" duration="3649" size="970626" />
<Group pts="526609" duration="3526" size="1542977" />
<Group pts="530196" duration="2952" size="874530" />
<Group pts="533199" duration="4387" size="1935020" />
<Group pts="537662" duration="9840" size="4465271" />
<Group pts="547672" duration="1804" size="772832" />
<Group pts="549507" duration="4715" size="1695886" />
<Group pts="554304" duration="7708" size="3219464" />
<Group pts="562145" duration="5002" size="1945945" />
<Group pts="567233" duration="5740" size="2206362" />
<Group pts="573073" duration="1927" size="755073" />
<Group pts="575033" duration="1927" size="681728" />
<Group pts="576993" duration="9840" size="3899859" />
<Group pts="587003" duration="4305" size="1799401" />
<Group pts="591382" duration="1804" size="707421" />
<Group pts="593218" duration="3280" size="969797" />
<Group pts="596554" duration="2255" size="637119" />
<Group pts="598848" duration="2091" size="612855" />
<Group pts="600975" duration="9840" size="4260417" />
<Group pts="610985" duration="9840" size="4019857" />
<Group pts="620995" duration="2542" size="1234310" />
<Group pts="623581" duration="2624" size="1125478" />
<Group pts="626251" duration="3526" size="1384635" />
<Group pts="629838" duration="4141" size="1552479" />
<Group pts="634050" duration="9799" size="2311063" />
<Group pts="644018" duration="9799" size="2983402" />
<Group pts="653987" duration="9758" size="4173556" />
<Group pts="663913" duration="3362" size="1337792" />
<Group pts="667333" duration="9799" size="2925237" />
<Group pts="677302" duration="2870" size="867772" />
<Group pts="680221" duration="9840" size="2350642" />
<Group pts="690231" duration="8364" size="2300373" />
<Group pts="698740" duration="9799" size="3275576" />
<Group pts="708708" duration="5904" size="2669155" />
<Group pts="714714" duration="9512" size="4862816" />
<Group pts="724390" duration="9840" size="3577251" />
<Group pts="734400" duration="4100" size="1490078" />
<Group pts="738571" duration="7749" size="3224623" />
<Group pts="746454" duration="5658" size="1812103" />
<Group pts="752210" duration="1599" size="505819" />
<Group pts="753836" duration="9840" size="2119368" />
<Group pts="763846" duration="3649" size="1087359" />
<Group pts="767558" duration="4756" size="1118663" />
<Group pts="772397" duration="2091" size="652057" />
<Group pts="774524" duration="2255" size="924390" />
<Group pts="776818" duration="4059" size="907932" />
<Group pts="780947" duration="4920" size="1440178" />
<Group pts="785952" duration="2296" size="738846" />
<Group pts="788288" duration="2993" size="991461" />
<Group pts="791332" duration="9840" size="2656453" />
<Group pts="801342" duration="4715" size="1288000" />
<Group pts="806139" duration="3649" size="1308755" />
<Group pts="809851" duration="9635" size="3000261" />
<Group pts="819652" duration="5248" size="1567305" />
<Group pts="824991" duration="9840" size="2302724" />
<Group pts="835001" duration="3403" size="641841" />
<Group pts="838463" duration="4223" size="1457400" />
<Group pts="842759" duration="3690" size="769549" />
<Group pts="846512" duration="7913" size="2957696" />
<Group pts="854562" duration="3321" size="1152725" />
<Group pts="857940" duration="3813" size="915069" />
<Group pts="861819" duration="4305" size="1676439" />
<Group pts="866199" duration="2829" size="728106" />
<Group pts="869077" duration="5371" size="1029694" />
<Group pts="874540" duration="2378" size="788763" />
<Group pts="876959" duration="2829" size="772617" />
<Group pts="879837" duration="4715" size="1669307" />
<Group pts="884634" duration="2091" size="604065" />
<Group pts="886761" duration="3854" size="1185060" />
<Group pts="890681" duration="2501" size="634168" />
<Group pts="893226" duration="1435" size="459062" />
<Group pts="894685" duration="1722" size="540715" />
<Group pts="896437" duration="1148" size="394308" />
<Group pts="897605" duration="1681" size="675884" />
<Group pts="899315" duration="2009" size="845129" />
<Group pts="901359" duration="1271" size="291329" />
<Group pts="902652" duration="1394" size="478255" />
<Group pts="904070" duration="1312" size="449644" />
<Group pts="905405" duration="1230" size="294167" />
<Group pts="906656" duration="1271" size="335302" />
<Group pts="907949" duration="3280" size="1110005" />
<Group pts="911285" duration="2460" size="986289" />
<Group pts="913788" duration="9840" size="4026122" />
<Group pts="923798" duration="1927" size="817735" />
<Group pts="925758" duration="9840" size="4538133" />
<Group pts="935768" duration="4510" size="1723580" />
<Group pts="940356" duration="1476" size="545227" />
<Group pts="941858" duration="3772" size="1191693" />
<Group pts="945695" duration="9840" size="4408963" />
<Group pts="955705" duration="9840" size="3917953" />
<Group pts="965715" duration="1271" size="408669" />
<Group pts="967008" duration="9840" size="3460219" />
<Group pts="977018" duration="9840" size="3747929" />
<Group pts="987028" duration="3075" size="1421194" />
<Group pts="990156" duration="9840" size="3803204" />
<Group pts="1000166" duration="1394" size="554026" />
<Group pts="1001584" duration="9799" size="3900996" />
<Group pts="1011552" duration="2419" size="1349303" />
<Group pts="1014013" duration="9840" size="3272960" />
<Group pts="1024023" duration="1189" size="484784" />
<Group pts="1025233" duration="9799" size="4034534" />
<Group pts="1035201" duration="9840" size="4302004" />
<Group pts="1045211" duration="8036" size="2064564" />
<Group pts="1053386" duration="8282" size="2268155" />
<Group pts="1061811" duration="4797" size="1017159" />
<Group pts="1066691" duration="3444" size="1231887" />
<Group pts="1070194" duration="5002" size="1193308" />
<Group pts="1075283" duration="1968" size="395430" />
<Group pts="1077285" duration="2706" size="1014768" />
<Group pts="1080037" duration="3280" size="685609" />
<Group pts="1083374" duration="4346" size="743181" />
<Group pts="1087795" duration="1353" size="330880" />
<Group pts="1089171" duration="1271" size="541438" />
<Group pts="1090464" duration="2583" size="1231444" />
<Group pts="1093092" duration="1681" size="413620" />
<Group pts="1094802" duration="2501" size="935101" />
<Group pts="1097346" duration="3157" size="666155" />
<Group pts="1100558" duration="2542" size="594322" />
<Group pts="1103144" duration="8856" size="3069429" />
<Group pts="1112153" duration="2296" size="772407" />
<Group pts="1114488" duration="3772" size="815976" />
<Group pts="1118326" duration="3198" size="743558" />
<Group pts="1121579" duration="4182" size="1560131" />
<Group pts="1125833" duration="1640" size="425898" />
<Group pts="1127501" duration="3403" size="926073" />
<Group pts="1130963" duration="3649" size="793709" />
<Group pts="1134675" duration="4387" size="1136349" />
<Group pts="1139138" duration="9840" size="2198106" />
<Group pts="1149148" duration="2132" size="515821" />
<Group pts="1151317" duration="3198" size="735007" />
<Group pts="1154570" duration="6519" size="2265465" />
<Group pts="1161202" duration="2255" size="691737" />
<Group pts="1163496" duration="5084" size="1860952" />
<Group pts="1168668" duration="9840" size="3209791" />
<Group pts="1178678" duration="1517" size="544131" />
<Group pts="1180221" duration="9840" size="2291190" />
<Group pts="1190231" duration="4510" size="1153629" />
<Group pts="1194819" duration="9840" size="3550218" />
<Group pts="1204829" duration="4100" size="1989596" />
<Group pts="1208999" duration="4633" size="2040055" />
<Group pts="1213713" duration="1968" size="521302" />
<Group pts="1215715" duration="7708" size="3205651" />
<Group pts="1223556" duration="9840" size="4394315" />
<Group pts="1233566" duration="9840" size="3303929" />
<Group pts="1243576" duration="1476" size="906932" />
<Group pts="1245077" duration="1517" size="639455" />
<Group pts="1246620" duration="9840" size="4311520" />
<Group pts="1256630" duration="9840" size="3990995" />
<Group pts="1266640" duration="4715" size="1363259" />
<Group pts="1271437" duration="1681" size="858459" />
<Group pts="1273147" duration="2706" size="895987" />
<Group pts="1275900" duration="5740" size="2069941" />
<Group pts="1281739" duration="2706" size="1502726" />
<Group pts="1284492" duration="3444" size="1506126" />
<Group pts="1287995" duration="9840" size="2565985" />
<Group pts="1298005" duration="8036" size="2365299" />
<Group pts="1306180" duration="7380" size="3010062" />
<Group pts="1313687" duration="9840" size="4386848" />
<Group pts="1323697" duration="3895" size="1743116" />
<Group pts="1327660" duration="984" size="428652" />
<Group pts="1328661" duration="5371" size="2219296" />
<Group pts="1334124" duration="3321" size="1497155" />
<Group pts="1337503" duration="4018" size="1693632" />
<Group pts="1341590" duration="1845" size="785836" />
<Group pts="1343467" duration="1107" size="425024" />
<Group pts="1344593" duration="1558" size="681963" />
<Group pts="1346178" duration="9840" size="4716974" />
<Group pts="1356188" duration="9184" size="4500295" />
<Group pts="1365531" duration="2214" size="968055" />
<Group pts="1367783" duration="9840" size="4792555" />
<Group pts="1377793" duration="9758" size="4511070" />
<Group pts="1387720" duration="9840" size="5039849" />
<Group pts="1397730" duration="9840" size="4760271" />
<Group pts="1407740" duration="1025" size="611269" />
<Group pts="1408782" duration="9799" size="4391988" />
<Group pts="1418751" duration="9840" size="4951381" />
<Group pts="1428761" duration="9840" size="4903997" />
<Group pts="1438771" duration="9840" size="4665406" />
<Group pts="1448781" duration="2911" size="1372468" />
<Group pts="1451742" duration="1435" size="725302" />
<Group pts="1453202" duration="9799" size="4547339" />
<Group pts="1463170" duration="2091" size="1290811" />
<Group pts="1465297" duration="9799" size="4619963" />
<Group pts="1475265" duration="943" size="500295" />
<Group pts="1476225" duration="9799" size="4470842" />
<Group pts="1486193" duration="943" size="569207" />
<Group pts="1487152" duration="1435" size="619617" />
<Group pts="1488612" duration="3690" size="1816326" />
<Group pts="1492366" duration="9799" size="4452436" />
<Group pts="1502334" duration="5125" size="2843296" />
<Group pts="1507548" duration="1558" size="826920" />
<Group pts="1509133" duration="9758" size="4673161" />
<Group pts="1519059" duration="1271" size="556777" />
<Group pts="1520352" duration="5289" size="2419002" />
<Group pts="1525733" duration="943" size="413068" />
<Group pts="1526692" duration="9799" size="4268482" />
<Group pts="1536660" duration="2419" size="1050849" />
<Group pts="1539121" duration="9840" size="4227113" />
<Group pts="1549131" duration="3157" size="1387585" />
<Group pts="1552342" duration="2009" size="973938" />
<Group pts="1554386" duration="1435" size="731788" />
<Group pts="1555846" duration="1312" size="518495" />
<Group pts="1557181" duration="1066" size="429466" />
<Group pts="1558265" duration="1845" size="746336" />
<Group pts="1560142" duration="2501" size="856888" />
<Group pts="1562686" duration="9799" size="4856562" />
<Group pts="1572654" duration="9840" size="5515463" />
<Group pts="1582664" duration="9799" size="4988416" />
<Group pts="1592633" duration="3280" size="1418876" />
<Group pts="1595969" duration="984" size="442422" />
<Group pts="1596970" duration="5535" size="2255558" />
<Group pts="1602601" duration="5166" size="1705345" />
<Group pts="1607856" duration="9840" size="3885212" />
<Group pts="1617866" duration="9799" size="5109695" />
<Group pts="1627835" duration="9799" size="4660751" />
<Group pts="1637803" duration="1312" size="638761" />
<Group pts="1639138" duration="9840" size="4460896" />
<Group pts="1649148" duration="9799" size="4326632" />
<Group pts="1659116" duration="9840" size="4162871" />
<Group pts="1669126" duration="9840" size="4163273" />
<Group pts="1679136" duration="9225" size="4076083" />
<Group pts="1688520" duration="2624" size="853547" />
<Group pts="1691190" duration="4510" size="1831792" />
<Group pts="1695777" duration="9840" size="4165573" />
<Group pts="1705787" duration="9840" size="4057575" />
<Group pts="1715797" duration="2501" size="1198124" />
<Group pts="1718342" duration="9799" size="3622626" />
<Group pts="1728310" duration="4059" size="2067673" />
<Group pts="1732439" duration="9594" size="2836784" />
<Group pts="1742199" duration="8364" size="2545434" />
<Group pts="1750707" duration="9799" size="3708600" />
<Group pts="1760676" duration="4182" size="1532248" />
<Group pts="1764930" duration="1763" size="660085" />
<Group pts="1766723" duration="1353" size="505879" />
<Group pts="1768100" duration="3895" size="1531632" />
<Group pts="1772062" duration="9799" size="4455744" />
<Group pts="1782030" duration="2050" size="890829" />
<Group pts="1784116" duration="1107" size="501355" />
<Group pts="1785242" duration="9840" size="4618271" />
<Group pts="1795252" duration="9676" size="3792592" />
<Group pts="1805095" duration="2706" size="858919" />
<Group pts="1807848" duration="1435" size="632396" />
<Group pts="1809308" duration="4305" size="1808031" />
<Group pts="1813687" duration="4469" size="1935782" />
<Group pts="1818233" duration="4264" size="1627707" />
<Group pts="1822571" duration="3280" size="598251" />
<Group pts="1825907" duration="6396" size="1634901" />
<Group pts="1832414" duration="3280" size="915516" />
<Group pts="1835751" duration="3936" size="951750" />
<Group pts="1839755" duration="4920" size="1511323" />
<Group pts="1844760" duration="1886" size="479451" />
<Group pts="1846678" duration="1066" size="369295" />
<Group pts="1847763" duration="2747" size="818065" />
<Group pts="1850557" duration="2993" size="798173" />
<Group pts="1853602" duration="4223" size="1259234" />
<Group pts="1857898" duration="1886" size="553008" />
<Group pts="1859816" duration="2952" size="837811" />
<Group pts="1862819" duration="1394" size="416714" />
<Group pts="1864237" duration="1189" size="352222" />
<Group pts="1865447" duration="9840" size="4165309" />
<Group pts="1875457" duration="9840" size="3902636" />
<Group pts="1885467" duration="7298" size="2889967" />
<Group pts="1892891" duration="9799" size="4836644" />
<Group pts="1902859" duration="9799" size="4282062" />
<Group pts="1912828" duration="9799" size="5227664" />
<Group pts="1922796" duration="3321" size="1287638" />
<Group pts="1926174" duration="9840" size="4150203" />
<Group pts="1936184" duration="7011" size="3380364" />
<Group pts="1943316" duration="1599" size="593912" />
<Group pts="1944943" duration="3362" size="1483473" />
<Group pts="1948363" duration="9799" size="4544293" />
<Group pts="1958331" duration="9840" size="4483748" />
<Group pts="1968341" duration="3690" size="1560832" />
<Group pts="1972095" duration="9840" size="3568234" />
<Group pts="1982105" duration="9799" size="3523941" />
<Group pts="1992073" duration="9799" size="5198608" />
<Group pts="2002042" duration="9840" size="4241943" />
<Group pts="2012052" duration="9840" size="5524997" />
<Group pts="2022062" duration="5412" size="1863051" />
<Group pts="2027567" duration="9758" size="2706033" />
<Group pts="2037494" duration="1927" size="965584" />
<Group pts="2039454" duration="9840" size="1756153" />
<Group pts="2049464" duration="9840" size="3363696" />
<Group pts="2059474" duration="2337" size="764440" />
<Group pts="2061851" duration="5330" size="1452903" />
<Group pts="2067274" duration="9840" size="3028779" />
<Group pts="2077284" duration="1066" size="473919" />
<Group pts="2078368" duration="6232" size="1508531" />
<Group pts="2084708" duration="9840" size="3057583" />
<Group pts="2094718" duration="9840" size="2727789" />
<Group pts="2104728" duration="5002" size="1898316" />
<Group pts="2109816" duration="9840" size="2518540" />
<Group pts="2119826" duration="6519" size="1458529" />
<Group pts="2126458" duration="2050" size="523143" />
<Group pts="2128543" duration="2050" size="854495" />
<Group pts="2130629" duration="9840" size="4052658" />
<Group pts="2140639" duration="1394" size="561863" />
<Group pts="2142057" duration="1107" size="451752" />
<Group pts="2143183" duration="2665" size="1000220" />
<Group pts="2145894" duration="2706" size="1143500" />
<Group pts="2148647" duration="5248" size="2191195" />
<Group pts="2153985" duration="1312" size="495272" />
<Group pts="2155320" duration="8118" size="3481988" />
<Group pts="2163578" duration="9840" size="3838686" />
<Group pts="2173588" duration="3772" size="1086523" />
<Group pts="2177425" duration="9840" size="2655027" />
<Group pts="2187435" duration="1968" size="770860" />
<Group pts="2189437" duration="7052" size="1903414" />
<Group pts="2196611" duration="9840" size="2441155" />
<Group pts="2206621" duration="3075" size="839040" />
<Group pts="2209749" duration="1968" size="654560" />
<Group pts="2211751" duration="3034" size="973808" />
<Group pts="2214838" duration="2337" size="490190" />
<Group pts="2217215" duration="5002" size="1610261" />
<Group pts="2222303" duration="3403" size="1193915" />
<Group pts="2225765" duration="3321" size="916821" />
<Group pts="2229144" duration="4551" size="1286037" />
<Group pts="2233773" duration="5412" size="1514445" />
<Group pts="2239279" duration="3772" size="1069135" />
<Group pts="2243116" duration="9758" size="3214384" />
<Group pts="2253042" duration="4059" size="1467358" />
<Group pts="2257172" duration="1558" size="424348" />
<Group pts="2258757" duration="9840" size="3436953" />
<Group pts="2268767" duration="9840" size="2794126" />
<Group pts="2278777" duration="1804" size="448933" />
<Group pts="2280612" duration="2091" size="592405" />
<Group pts="2282739" duration="1722" size="532334" />
<Group pts="2284491" duration="9840" size="4713171" />
<Group pts="2294501" duration="9840" size="3134098" />
<Group pts="2304511" duration="9799" size="1212322" />
<Group pts="2314479" duration="9799" size="3367738" />
<Group pts="2324447" duration="9799" size="3504759" />
<Group pts="2334415" duration="9799" size="4003209" />
<Group pts="2344384" duration="9799" size="2819753" />
<Group pts="2354352" duration="9799" size="2890331" />
<Group pts="2364320" duration="9840" size="3262738" />
<Group pts="2374330" duration="9799" size="3405231" />
<Group pts="2384299" duration="1271" size="405593" />
<Group pts="2385592" duration="9799" size="3051220" />
<Group pts="2395560" duration="9799" size="3584037" />
<Group pts="2405528" duration="9799" size="3231171" />
<Group pts="2415496" duration="9799" size="5595757" />
<Group pts="2425465" duration="9840" size="5112770" />
<Group pts="2435475" duration="943" size="511366" />
<Group pts="2436434" duration="9840" size="4210316" />
<Group pts="2446444" duration="9840" size="4587936" />
<Group pts="2456454" duration="9799" size="5243277" />
<Group pts="2466422" duration="1066" size="511605" />
<Group pts="2467507" duration="5207" size="1554975" />
<Group pts="2472804" duration="2870" size="872275" />
<Group pts="2475723" duration="9840" size="3115380" />
<Group pts="2485733" duration="1435" size="540991" />
<Group pts="2487193" duration="9840" size="3981707" />
<Group pts="2497203" duration="3157" size="1407115" />
<Group pts="2500415" duration="5576" size="3020745" />
<Group pts="2506087" duration="9840" size="4344952" />
<Group pts="2516097" duration="9840" size="3865179" />
<Group pts="2526107" duration="9840" size="2653617" />
<Group pts="2536117" duration="9840" size="2122996" />
<Group pts="2546127" duration="9840" size="2440034" />
<Group pts="2556137" duration="9840" size="2017761" />
<Group pts="2566147" duration="9840" size="2723866" />
<Group pts="2576157" duration="2214" size="650357" />
<Group pts="2578409" duration="9840" size="2532500" />
<Group pts="2588419" duration="1845" size="490682" />
<Group pts="2590296" duration="6273" size="1275591" />
<Group pts="2596677" duration="9840" size="2182668" />
<Group pts="2606687" duration="8446" size="2391764" />
<Group pts="2615279" duration="8077" size="2417400" />
<Group pts="2623496" duration="7175" size="1933688" />
<Group pts="2630795" duration="9840" size="2056302" />
<Group pts="2640805" duration="6683" size="1346509" />
<Group pts="2647603" duration="9840" size="2345560" />
<Group pts="2657613" duration="9840" size="2453770" />
<Group pts="2667623" duration="2050" size="534814" />
<Group pts="2669709" duration="3198" size="843960" />
<Group pts="2672962" duration="1230" size="390170" />
<Group pts="2674213" duration="2050" size="864388" />
<Group pts="2676299" duration="3362" size="943877" />
<Group pts="2679719" duration="4059" size="1227886" />
<Group pts="2683848" duration="3321" size="1075538" />
<Group pts="2687226" duration="9840" size="3033210" />
<Group pts="2697236" duration="9840" size="4332660" />
<Group pts="2707246" duration="2501" size="620152" />
<Group pts="2709790" duration="2829" size="727254" />
<Group pts="2712668" duration="3239" size="776747" />
<Group pts="2715963" duration="3321" size="826208" />
<Group pts="2719342" duration="6437" size="2409739" />
<Group pts="2725890" duration="2009" size="501161" />
<Group pts="2727934" duration="6273" size="1817778" />
<Group pts="2734315" duration="1640" size="376783" />
<Group pts="2735983" duration="2460" size="457097" />
<Group pts="2738486" duration="2583" size="687491" />
<Group pts="2741113" duration="2214" size="603866" />
<Group pts="2743366" duration="1886" size="480987" />
<Group pts="2745284" duration="2706" size="745509" />
<Group pts="2748037" duration="9840" size="2607464" />
<Group pts="2758047" duration="4223" size="1458425" />
<Group pts="2762343" duration="4223" size="1843305" />
<Group pts="2766639" duration="2378" size="604080" />
<Group pts="2769058" duration="1353" size="475141" />
<Group pts="2770434" duration="1394" size="758615" />
<Group pts="2771852" duration="1107" size="354124" />
<Group pts="2772979" duration="2993" size="1225428" />
<Group pts="2776023" duration="4346" size="1675563" />
<Group pts="2780444" duration="1353" size="404689" />
<Group pts="2781821" duration="3731" size="1665100" />
<Group pts="2785616" duration="2214" size="745686" />
<Group pts="2787868" duration="3075" size="1391355" />
<Group pts="2790997" duration="1107" size="333841" />
<Group pts="2792123" duration="7872" size="3267442" />
<Group pts="2800131" duration="2255" size="847086" />
<Group pts="2802425" duration="9799" size="3962130" />
<Group pts="2812393" duration="2952" size="1253334" />
<Group pts="2815396" duration="9840" size="3641918" />
<Group pts="2825406" duration="3034" size="978383" />
<Group pts="2828492" duration="2747" size="762893" />
<Group pts="2831287" duration="9799" size="2676913" />
<Group pts="2841255" duration="9840" size="2213210" />
<Group pts="2851265" duration="3526" size="704873" />
<Group pts="2854852" duration="5576" size="1005951" />
<Group pts="2860524" duration="9840" size="1752958" />
<Group pts="2870534" duration="2624" size="567895" />
<Group pts="2873204" duration="1558" size="336701" />
<Group pts="2874789" duration="2829" size="522837" />
<Group pts="2877666" duration="7339" size="1934700" />
<Group pts="2885132" duration="4018" size="1273581" />
<Group pts="2889220" duration="3198" size="997309" />
<Group pts="2892473" duration="3403" size="954688" />
<Group pts="2895935" duration="5084" size="1418068" />
<Group pts="2901107" duration="4715" size="1985173" />
<Group pts="2905903" duration="6314" size="1895127" />
<Group pts="2912326" duration="9840" size="3243917" />
<Group pts="2922336" duration="6109" size="2111980" />
<Group pts="2928551" duration="5248" size="2144763" />
<Group pts="2933889" duration="4182" size="1277451" />
<Group pts="2938144" duration="5084" size="1296058" />
<Group pts="2943315" duration="7790" size="2688389" />
<Group pts="2951240" duration="3157" size="902999" />
<Group pts="2954452" duration="4182" size="1080539" />
<Group pts="2958706" duration="4551" size="2065235" />
<Group pts="2963335" duration="4674" size="1376428" />
<Group pts="2968090" duration="9840" size="3373700" />
<Group pts="2978100" duration="9840" size="3734365" />
<Group pts="2988110" duration="3075" size="1062238" />
<Group pts="2991238" duration="4182" size="1065497" />
<Group pts="2995493" duration="2624" size="519017" />
<Group pts="2998162" duration="9840" size="3850105" />
<Group pts="3008172" duration="1517" size="818635" />
<Group pts="3009715" duration="9840" size="667585" />
<Group pts="3019725" duration="9840" size="2292205" />
<Group pts="3029735" duration="9840" size="2882870" />
<Group pts="3039745" duration="9840" size="2920653" />
<Group pts="3049755" duration="9840" size="3346320" />
<Group pts="3059765" duration="2460" size="666230" />
<Group pts="3062268" duration="1927" size="457771" />
<Group pts="3064228" duration="6314" size="1565775" />
<Group pts="3070651" duration="9840" size="1368613" />
<Group pts="3080661" duration="6314" size="798517" />
<Group pts="3087084" duration="9840" size="1866156" />
<Group pts="3097094" duration="4961" size="766390" />
<Group pts="3102141" duration="6027" size="1531937" />
<Group pts="3108272" duration="2419" size="578017" />
<Group pts="3110733" duration="3075" size="484503" />
<Group pts="3113861" duration="9840" size="2101911" />
<Group pts="3123871" duration="9840" size="1868902" />
<Group pts="3133881" duration="1148" size="244826" />
<Group pts="3135049" duration="9840" size="1687818" />
<Group pts="3145059" duration="2952" size="495661" />
<Group pts="3148062" duration="9840" size="2112252" />
<Group pts="3158072" duration="2419" size="595722" />
<Group pts="3160532" duration="9840" size="2294022" />
<Group pts="3170542" duration="9840" size="2482946" />
<Group pts="3180552" duration="3649" size="913505" />
<Group pts="3184264" duration="9840" size="2520287" />
<Group pts="3194274" duration="9307" size="2383942" />
<Group pts="3203742" duration="9840" size="2312737" />
<Group pts="3213752" duration="5084" size="1323789" />
<Group pts="3218924" duration="8241" size="1955082" />
<Group pts="3227307" duration="9840" size="2252896" />
<Group pts="3237317" duration="9840" size="2503449" />
<Group pts="3247327" duration="1025" size="303386" />
<Group pts="3248370" duration="9840" size="2426879" />
<Group pts="3258380" duration="2870" size="660962" />
<Group pts="3261300" duration="4469" size="1217850" />
<Group pts="3265846" duration="9840" size="2220309" />
<Group pts="3275856" duration="5617" size="1161823" />
<Group pts="3281570" duration="3854" size="1068593" />
<Group pts="3285491" duration="9840" size="2483033" />
<Group pts="3295501" duration="9840" size="2873870" />
<Group pts="3305511" duration="3239" size="905419" />
<Group pts="3308806" duration="9840" size="3057924" />
<Group pts="3318816" duration="9512" size="2911288" />
<Group pts="3328492" duration="9430" size="2982097" />
<Group pts="3338085" duration="7298" size="2253549" />
<Group pts="3345509" duration="984" size="310460" />
<Group pts="3346510" duration="1066" size="381304" />
<Group pts="3347594" duration="9840" size="2851878" />
<Group pts="3357604" duration="9840" size="2855180" />
<Group pts="3367614" duration="4551" size="1290204" />
<Group pts="3372244" duration="1804" size="678953" />
<Group pts="3374079" duration="1230" size="330546" />
<Group pts="3375330" duration="9840" size="2481163" />
<Group pts="3385340" duration="9840" size="2572728" />
<Group pts="3395350" duration="3362" size="1141662" />
<Group pts="3398770" duration="2542" size="797630" />
<Group pts="3401356" duration="4551" size="1465334" />
<Group pts="3405986" duration="9840" size="3085163" />
<Group pts="3415996" duration="1845" size="482582" />
<Group pts="3417873" duration="7790" size="2468228" />
<Group pts="3425797" duration="1681" size="482152" />
<Group pts="3427507" duration="4838" size="1417027" />
<Group pts="3432429" duration="5494" size="1445360" />
<Group pts="3438018" duration="4756" size="1234448" />
<Group pts="3442856" duration="3198" size="1059699" />
<Group pts="3446109" duration="8856" size="2818740" />
<Group pts="3455118" duration="3608" size="760385" />
<Group pts="3458789" duration="2747" size="666087" />
<Group pts="3461583" duration="5945" size="1598457" />
<Group pts="3467631" duration="3403" size="987788" />
<Group pts="3471093" duration="1394" size="406520" />
<Group pts="3472511" duration="3075" size="881170" />
<Group pts="3475639" duration="9840" size="2901909" />
<Group pts="3485649" duration="9840" size="2771121" />
<Group pts="3495659" duration="9840" size="2441989" />
<Group pts="3505669" duration="4264" size="1048424" />
<Group pts="3510007" duration="2501" size="576968" />
<Group pts="3512551" duration="9840" size="2959134" />
<Group pts="3522561" duration="9799" size="3208965" />
<Group pts="3532529" duration="1353" size="475536" />
<Group pts="3533905" duration="2337" size="724262" />
<Group pts="3536283" duration="1517" size="392919" />
<Group pts="3537826" duration="3444" size="1284576" />
<Group pts="3541329" duration="2091" size="518247" />
<Group pts="3543457" duration="4264" size="1243947" />
<Group pts="3547794" duration="6150" size="1893466" />
<Group pts="3554051" duration="7134" size="1947694" />
<Group pts="3561308" duration="2501" size="909364" />
<Group pts="3563852" duration="2870" size="926098" />
<Group pts="3566772" duration="2829" size="903702" />
<Group pts="3569649" duration="2214" size="802097" />
<Group pts="3571902" duration="5084" size="1580570" />
<Group pts="3577074" duration="4059" size="1342864" />
<Group pts="3581203" duration="2378" size="702854" />
<Group pts="3583622" duration="3239" size="1065385" />
<Group pts="3586917" duration="1804" size="550190" />
<Group pts="3588752" duration="1681" size="599639" />
<Group pts="3590462" duration="4182" size="1583479" />
<Group pts="3594716" duration="7380" size="2515885" />
<Group pts="3602224" duration="2091" size="651226" />
<Group pts="3604351" duration="9799" size="3418968" />
<Group pts="3614319" duration="9840" size="3248263" />
<Group pts="3624329" duration="9676" size="3244034" />
<Group pts="3634172" duration="5740" size="2037012" />
<Group pts="3640011" duration="7544" size="2317373" />
<Group pts="3647686" duration="2296" size="613679" />
<Group pts="3650021" duration="9840" size="3212189" />
<Group pts="3660031" duration="5043" size="1521409" />
<Group pts="3665162" duration="4592" size="1465156" />
<Group pts="3669833" duration="2583" size="740068" />
<Group pts="3672460" duration="9799" size="3104168" />
<Group pts="3682429" duration="8159" size="2740719" />
<Group pts="3690729" duration="3485" size="1038467" />
<Group pts="3694274" duration="9840" size="2901374" />
<Group pts="3704284" duration="2214" size="793089" />
<Group pts="3706536" duration="7011" size="2272852" />
<Group pts="3713668" duration="5658" size="1820081" />
<Group pts="3719424" duration="2952" size="965540" />
<Group pts="3722427" duration="2378" size="718774" />
<Group pts="3724846" duration="7462" size="2344771" />
<Group pts="3732437" duration="9840" size="3090319" />
<Group pts="3742447" duration="6724" size="1865554" />
<Group pts="3749287" duration="3157" size="656090" />
<Group pts="3752499" duration="7462" size="2025102" />
<Group pts="3760090" duration="1927" size="569216" />
<Group pts="3762050" duration="9840" size="3121868" />
<Group pts="3772060" duration="3485" size="1290046" />
<Group pts="3775605" duration="1804" size="609258" />
<Group pts="3777440" duration="2706" size="634318" />
<Group pts="3780193" duration="1066" size="353496" />
<Group pts="3781278" duration="2337" size="510582" />
<Group pts="3783655" duration="9840" size="2818053" />
<Group pts="3793665" duration="2583" size="933262" />
<Group pts="3796293" duration="2624" size="574576" />
<Group pts="3798962" duration="9389" size="2830430" />
<Group pts="3808513" duration="8774" size="1714853" />
<Group pts="3817439" duration="2214" size="489791" />
<Group pts="3819691" duration="2214" size="567312" />
<Group pts="3821943" duration="9594" size="2605425" />
<Group pts="3831703" duration="1517" size="525772" />
<Group pts="3833246" duration="1353" size="487793" />
<Group pts="3834622" duration="5699" size="1190607" />
<Group pts="3840420" duration="7462" size="2494914" />
<Group pts="3848011" duration="3690" size="1125909" />
<Group pts="3851765" duration="1435" size="366214" />
<Group pts="3853224" duration="3280" size="971226" />
<Group pts="3856561" duration="2050" size="608420" />
<Group pts="3858646" duration="9840" size="3843323" />
<Group pts="3868656" duration="5166" size="1856908" />
<Group pts="3873912" duration="2214" size="697325" />
<Group pts="3876164" duration="3157" size="860066" />
<Group pts="3879376" duration="8815" size="2736492" />
<Group pts="3888343" duration="1640" size="508249" />
<Group pts="3890011" duration="2255" size="718124" />
<Group pts="3892305" duration="1312" size="498899" />
<Group pts="3893640" duration="9799" size="3405980" />
<Group pts="3903608" duration="9840" size="3095494" />
<Group pts="3913618" duration="1722" size="586560" />
<Group pts="3915370" duration="9799" size="2711016" />
<Group pts="3925338" duration="9799" size="3106292" />
<Group pts="3935306" duration="9512" size="3297102" />
<Group pts="3944983" duration="1763" size="693461" />
<Group pts="3946776" duration="1681" size="582692" />
<Group pts="3948486" duration="9799" size="3960760" />
<Group pts="3958455" duration="1189" size="546455" />
<Group pts="3959664" duration="6806" size="2736252" />
<Group pts="3966588" duration="2173" size="639701" />
<Group pts="3968798" duration="9799" size="3873611" />
<Group pts="3978766" duration="9799" size="5046067" />
<Group pts="3988735" duration="1271" size="737037" />
<Group pts="3990028" duration="6560" size="2076221" />
<Group pts="3996701" duration="1927" size="527482" />
<Group pts="3998661" duration="8282" size="3074141" />
<Group pts="4007086" duration="9799" size="4639351" />
<Group pts="4017055" duration="9799" size="4753694" />
<Group pts="4027023" duration="7831" size="3584411" />
<Group pts="4034989" duration="9840" size="3553552" />
<Group pts="4044999" duration="9840" size="3566248" />
<Group pts="4055009" duration="2460" size="927024" />
<Group pts="4057512" duration="9840" size="3317508" />
<Group pts="4067522" duration="2829" size="869776" />
<Group pts="4070400" duration="9799" size="3750780" />
<Group pts="4080368" duration="9799" size="3560754" />
<Group pts="4090336" duration="9840" size="3103241" />
<Group pts="4100346" duration="2419" size="839526" />
<Group pts="4102807" duration="7585" size="2181877" />
<Group pts="4110523" duration="4141" size="1321752" />
<Group pts="4114736" duration="2624" size="1260929" />
<Group pts="4117405" duration="1640" size="677481" />
<Group pts="4119073" duration="1927" size="631412" />
<Group pts="4121034" duration="1845" size="632919" />
<Group pts="4122910" duration="3936" size="1433707" />
<Group pts="4126914" duration="2009" size="621006" />
<Group pts="4128958" duration="2296" size="886955" />
<Group pts="4131294" duration="5125" size="1668458" />
<Group pts="4136507" duration="2624" size="836501" />
<Group pts="4139177" duration="2050" size="867774" />
<Group pts="4141262" duration="1927" size="760205" />
<Group pts="4143222" duration="5248" size="1811641" />
<Group pts="4148561" duration="1476" size="482419" />
<Group pts="4150063" duration="4100" size="1480747" />
<Group pts="4154233" duration="9840" size="3278754" />
<Group pts="4164243" duration="3526" size="1177958" />
<Group pts="4167830" duration="4059" size="1452382" />
<Group pts="4171959" duration="3977" size="1112327" />
<Group pts="4176005" duration="3157" size="937974" />
<Group pts="4179217" duration="2214" size="794365" />
<Group pts="4181469" duration="2583" size="878101" />
<Group pts="4184097" duration="6314" size="3110013" />
<Group pts="4190520" duration="9840" size="3366977" />
<Group pts="4200530" duration="9840" size="3429416" />
<Group pts="4210540" duration="9840" size="2523037" />
<Group pts="4220550" duration="1558" size="520768" />
<Group pts="4222135" duration="3239" size="1043736" />
<Group pts="4225430" duration="9840" size="2170808" />
<Group pts="4235440" duration="9799" size="3150358" />
<Group pts="4245408" duration="7339" size="3561769" />
<Group pts="4252874" duration="6232" size="2028702" />
<Group pts="4259213" duration="6847" size="2123812" />
<Group pts="4266179" duration="2009" size="803559" />
<Group pts="4268222" duration="6232" size="2327329" />
<Group pts="4274562" duration="1968" size="625213" />
<Group pts="4276564" duration="3239" size="1219101" />
<Group pts="4279859" duration="9840" size="3494432" />
<Group pts="4289869" duration="9840" size="4043202" />
<Group pts="4299879" duration="2870" size="1078049" />
<Group pts="4302799" duration="9840" size="4184104" />
<Group pts="4312809" duration="9799" size="4657978" />
<Group pts="4322777" duration="9840" size="4646347" />
<Group pts="4332787" duration="9799" size="4444384" />
<Group pts="4342755" duration="9840" size="4352489" />
<Group pts="4352765" duration="9799" size="3949493" />
<Group pts="4362733" duration="9840" size="3755808" />
<Group pts="4372743" duration="9799" size="3721000" />
<Group pts="4382712" duration="9799" size="4147240" />
<Group pts="4392680" duration="9840" size="4635587" />
<Group pts="4402690" duration="9840" size="4192138" />
<Group pts="4412700" duration="9799" size="4133850" />
<Group pts="4422668" duration="9799" size="4651609" />
<Group pts="4432637" duration="9799" size="4365306" />
<Group pts="4442605" duration="9840" size="4345414" />
<Group pts="4452615" duration="3034" size="1096514" />
<Group pts="4455701" duration="2132" size="803874" />
<Group pts="4457870" duration="9840" size="3511281" />
<Group pts="4467880" duration="7093" size="2175058" />
<Group pts="4475096" duration="4551" size="1258847" />
<Group pts="4479725" duration="1845" size="582896" />
<Group pts="4481602" duration="6847" size="2310034" />
<Group pts="4488567" duration="2214" size="720546" />
<Group pts="4490820" duration="1312" size="424779" />
<Group pts="4492154" duration="9840" size="3655837" />
<Group pts="4502164" duration="2050" size="694455" />
<Group pts="4504250" duration="9840" size="2755119" />
<Group pts="4514260" duration="5535" size="1843721" />
<Group pts="4519890" duration="2132" size="740562" />
<Group pts="4522059" duration="1558" size="630494" />
<Group pts="4523644" duration="9840" size="3410618" />
<Group pts="4533654" duration="9840" size="3229079" />
<Group pts="4543664" duration="2706" size="868573" />
<Group pts="4546417" duration="9840" size="3128000" />
<Group pts="4556427" duration="4182" size="1461452" />
<Group pts="4560681" duration="1230" size="362430" />
<Group pts="4561932" duration="1599" size="559710" />
<Group pts="4563559" duration="1189" size="370485" />
<Group pts="4564769" duration="2542" size="1038769" />
<Group pts="4567354" duration="1886" size="612052" />
<Group pts="4569273" duration="1394" size="577662" />
<Group pts="4570691" duration="3813" size="1586581" />
<Group pts="4574570" duration="9758" size="3505969" />
<Group pts="4584497" duration="9840" size="3339996" />
<Group pts="4594507" duration="5863" size="1885898" />
<Group pts="4600471" duration="7175" size="2150734" />
<Group pts="4607770" duration="9840" size="2777745" />
<Group pts="4617780" duration="1640" size="679937" />
<Group pts="4619448" duration="2378" size="998500" />
<Group pts="4621867" duration="9799" size="4219488" />
<Group pts="4631836" duration="9840" size="4272032" />
<Group pts="4641846" duration="9840" size="3356605" />
<Group pts="4651856" duration="4428" size="1436521" />
<Group pts="4656360" duration="9799" size="2782562" />
<Group pts="4666328" duration="5535" size="759208" />
<Group pts="4671959" duration="5412" size="2115912" />
<Group pts="4677464" duration="7503" size="1764963" />
<Group pts="4685097" duration="7011" size="1320756" />
<Group pts="4692229" duration="4387" size="1216507" />
<Group pts="4696692" duration="3157" size="644175" />
<Group pts="4699904" duration="3485" size="945020" />
<Group pts="4703449" duration="5699" size="1451839" />
<Group pts="4709246" duration="6068" size="1441772" />
<Group pts="4715419" duration="3034" size="1050620" />
<Group pts="4718505" duration="4059" size="1084793" />
<Group pts="4722635" duration="9840" size="2241811" />
<Group pts="4732645" duration="9840" size="2772370" />
<Group pts="4742655" duration="5863" size="1771872" />
<Group pts="4748619" duration="8692" size="2344277" />
<Group pts="4757461" duration="3977" size="979010" />
<Group pts="4761507" duration="9840" size="2922544" />
<Group pts="4771517" duration="3567" size="1113573" />
<Group pts="4775145" duration="9840" size="2645264" />
<Group pts="4785155" duration="9840" size="2658866" />
<Group pts="4795165" duration="1353" size="415086" />
<Group pts="4796542" duration="2624" size="995437" />
<Group pts="4799211" duration="9717" size="2639215" />
<Group pts="4809096" duration="1968" size="621590" />
<Group pts="4811098" duration="9840" size="603434" />
<Group pts="4821108" duration="8733" size="1425903" />
<Group pts="4829992" duration="9840" size="3265068" />
<Group pts="4840002" duration="9512" size="3530106" />
<Group pts="4849678" duration="2583" size="717687" />
<Group pts="4852306" duration="3854" size="1562692" />
<Group pts="4856226" duration="4182" size="1266076" />
<Group pts="4860481" duration="3649" size="1118024" />
<Group pts="4864193" duration="9840" size="3062182" />
<Group pts="4874203" duration="3403" size="1379848" />
<Group pts="4877664" duration="6027" size="1916392" />
<Group pts="4883796" duration="4510" size="1379446" />
<Group pts="4888384" duration="4387" size="1785054" />
<Group pts="4892846" duration="4469" size="1759466" />
<Group pts="4897393" duration="3936" size="1530417" />
<Group pts="4901397" duration="4100" size="1319687" />
<Group pts="4905567" duration="5699" size="1671926" />
<Group pts="4911365" duration="7913" size="2266327" />
<Group pts="4919415" duration="3280" size="952119" />
<Group pts="4922751" duration="6724" size="2026958" />
<Group pts="4929591" duration="9840" size="2622955" />
<Group pts="4939601" duration="7011" size="2646261" />
<Group pts="4946733" duration="4141" size="1468516" />
<Group pts="4950946" duration="6027" size="1742465" />
<Group pts="4957077" duration="9840" size="3683845" />
<Group pts="4967087" duration="9430" size="3762518" />
<Group pts="4976680" duration="3280" size="1643709" />
<Group pts="4980017" duration="6314" size="3340018" />
<Group pts="4986440" duration="3198" size="1630885" />
<Group pts="4989693" duration="3157" size="1745631" />
<Group pts="4992905" duration="3075" size="1663338" />
<Group pts="4996033" duration="3157" size="1709042" />
<Group pts="4999244" duration="3321" size="1596799" />
<Group pts="5002623" duration="9102" size="4382912" />
<Group pts="5011882" duration="2952" size="1628414" />
<Group pts="5014885" duration="6027" size="3128815" />
<Group pts="5021016" duration="6150" size="3056040" />
<Group pts="5027272" duration="3075" size="1848491" />
<Group pts="5030400" duration="9061" size="4492203" />
<Group pts="5039618" duration="9799" size="3667212" />
<Group pts="5049586" duration="9840" size="332117" />
<Group pts="5059596" duration="9840" size="389817" />
<Group pts="5069606" duration="9840" size="404118" />
<Group pts="5079616" duration="9840" size="376595" />
<Group pts="5089626" duration="9840" size="405920" />
<Group pts="5099636" duration="9840" size="389958" />
<Group pts="5109646" duration="9840" size="390384" />
<Group pts="5119656" duration="9840" size="386758" />
<Group pts="5129666" duration="9840" size="408674" />
<Group pts="5139676" duration="9840" size="395428" />
<Group pts="5149686" duration="9840" size="371477" />
<Group pts="5159696" duration="9840" size="383927" />
<Group pts="5169706" duration="9840" size="386673" />
<Group pts="5179716" duration="9840" size="403341" />
<Group pts="5189726" duration="9840" size="414140" />
<Group pts="5199736" duration="9840" size="397156" />
<Group pts="5209746" duration="9840" size="364601" />
<Group pts="5219756" duration="9840" size="371659" />
<Group pts="5229766" duration="9840" size="448566" />
<Group pts="5239776" duration="9840" size="416969" />
<Group pts="5249786" duration="9840" size="394954" />
<Group pts="5259796" duration="9840" size="419373" />
<Group pts="5269806" duration="9840" size="407729" />
<Group pts="5279816" duration="9840" size="415217" />
<Group pts="5289826" duration="9840" size="423315" />
<Group pts="5299836" duration="9840" size="411721" />
<Group pts="5309846" duration="9840" size="454347" />
<Group pts="5319856" duration="9840" size="425841" />
<Group pts="5329866" duration="9840" size="495774" />
<Group pts="5339876" duration="3895" size="3188841" />
<Group pts="5343839" duration="9840" size="2904747" />
<Group pts="5353849" duration="1066" size="84321" />
</VideoStream>
